jqpd/__init__.py
jqpd/jqpd.py
tests/__init__.py
tests/test_jqpd.py
jqpd-0.0.4.dist-info/LICENSE.txt
jqpd-0.0.4.dist-info/METADATA
jqpd-0.0.4.dist-info/WHEEL
jqpd-0.0.4.dist-info/top_level.txt
jqpd-0.0.4.dist-info/RECORD
