Metadata-Version: 2.1
Name: jqpd
Version: 0.0.4
Summary: implementation of jqpd
Home-page: UNKNOWN
Author: Imran Khan
Author-email: iakhan@utexas.edu
License: UNKNOWN
Keywords: python,jqpd
Platform: UNKNOWN
Classifier: Programming Language :: Python :: 3
Classifier: License :: OSI Approved :: MIT License
Classifier: Operating System :: OS Independent
Requires-Python: >=3.6
Requires-Dist: pandas
Requires-Dist: numpy
Requires-Dist: scipy
